reporting_endpoints/__init__.py
reporting_endpoints/admin.py
reporting_endpoints/apps.py
reporting_endpoints/middleware.py
reporting_endpoints/models.py
reporting_endpoints/py.typed
reporting_endpoints/views.py
reporting_endpoints/migrations/0001_initial.py
reporting_endpoints/migrations/0002_add_disposition_unknown.py
reporting_endpoints/migrations/__init__.py
django_reporting_endpoints-0.9.5.dist-info/LICENSE
django_reporting_endpoints-0.9.5.dist-info/METADATA
django_reporting_endpoints-0.9.5.dist-info/WHEEL
django_reporting_endpoints-0.9.5.dist-info/top_level.txt
django_reporting_endpoints-0.9.5.dist-info/RECORD
