Metadata-Version: 2.1
Name: django_reporting_endpoints
Version: 0.9.5
Summary: "Django app for receiving browser's Reporting API reports."
Home-page: https://github.com/seporaitis/django-reporting-endpoints
Author: Julius Seporaitis
Author-email: julius@seporaitis.net
License: MIT
Project-URL: Documentation, https://django-reporting-endpoints.readthedocs.io/
Project-URL: Changelog, https://django-reporting-endpoints.readthedocs.io/en/latest/changelog.html
Project-URL: Twitter, https://twitter.com/seporaitis
Keywords: Django
Classifier: Development Status :: 5 - Production/Stable
Classifier: Framework :: Django :: 3.2
Classifier: Framework :: Django :: 4.0
Classifier: Framework :: Django :: 4.1
Classifier: Framework :: Django :: 4.2
Classifier: Framework :: Django :: 5.0
Classifier: Intended Audience :: Developers
Classifier: License :: OSI Approved :: MIT License
Classifier: Natural Language :: English
Classifier: Operating System :: OS Independent
Classifier: Programming Language :: Python :: 3
Classifier: Programming Language :: Python :: 3 :: Only
Classifier: Programming Language :: Python :: 3.8
Classifier: Programming Language :: Python :: 3.9
Classifier: Programming Language :: Python :: 3.10
Classifier: Programming Language :: Python :: 3.11
Classifier: Programming Language :: Python :: 3.12
Classifier: Programming Language :: Python :: Implementation :: CPython
Classifier: Typing :: Typed
Requires-Python: >=3.8
License-File: LICENSE
Requires-Dist: Django >=3.2
Requires-Dist: django-csp
